ml_engine/__init__.py
ml_engine/models.py
ml_engine/optimization.py
ml_engine/data/__init__.py
ml_engine/test/__init__.py
ml_engine-0.1.dist-info/LICENSE.txt
ml_engine-0.1.dist-info/METADATA
ml_engine-0.1.dist-info/WHEEL
ml_engine-0.1.dist-info/top_level.txt
ml_engine-0.1.dist-info/RECORD
